autocert/__init__.py
autocert/admin.py
autocert/apps.py
autocert/middleware.py
autocert/models.py
autocert/settings.py
autocert/tests.py
autocert/management/__init__.py
autocert/management/commands/__init__.py
autocert/management/commands/renew_all_expiring_soon.py
autocert/management/commands/write_certs.py
autocert/migrations/0001_initial.py
autocert/migrations/0002_update_domain_fields.py
autocert/migrations/__init__.py
django_autocert-0.1.7.dist-info/LICENSE
django_autocert-0.1.7.dist-info/METADATA
django_autocert-0.1.7.dist-info/WHEEL
django_autocert-0.1.7.dist-info/top_level.txt
django_autocert-0.1.7.dist-info/RECORD
