Metadata-Version: 2.1
Name: django-autocert
Version: 0.1.7
Summary: Automatic SSL certificates from Let's Encrypt for Django projects
Home-page: https://github.com/farrepa/django-autocert/
Author: Patrick Farrell
Author-email: p@farrell.io
License: MIT
Keywords: django ssl certificate acme
Platform: UNKNOWN
Classifier: Development Status :: 4 - Beta
Classifier: Intended Audience :: Developers
Classifier: Topic :: Software Development :: Build Tools
Classifier: License :: OSI Approved :: MIT License
Classifier: Programming Language :: Python :: 2
Classifier: Programming Language :: Python :: 2.7
Classifier: Programming Language :: Python :: 3
Requires-Dist: acme (>=0.9.3)
Requires-Dist: Django (>=1.8)
Requires-Dist: urllib3
Requires-Dist: josepy
